msr/VERSION
msr/__init__.py
msr_kouyang-0.1.9.data/scripts/msr
msr_kouyang-0.1.9.dist-info/LICENSE
msr_kouyang-0.1.9.dist-info/METADATA
msr_kouyang-0.1.9.dist-info/WHEEL
msr_kouyang-0.1.9.dist-info/top_level.txt
msr_kouyang-0.1.9.dist-info/RECORD
