Metadata-Version: 2.1
Name: msr-kouyang
Version: 0.1.9
Summary: Symops coding challenge
Home-page: https://github.com/symopsio/backend-challenge
Author: Kevin Ouyang
Author-email: kevinhouyang@gmail.com
License: UNKNOWN
Platform: UNKNOWN
Classifier: Programming Language :: Python :: 3
Classifier: License :: OSI Approved :: MIT License
Classifier: Operating System :: OS Independent
Requires-Python: >=3.6
Requires-Dist: requests
Requires-Dist: argparse
Requires-Dist: texttable
